superverse/__init__.py
superverse/annotators/__init__.py
superverse/annotators/base.py
superverse/annotators/core.py
superverse/annotators/utils.py
superverse/assets/__init__.py
superverse/assets/downloader.py
superverse/assets/list.py
superverse/classification/__init__.py
superverse/classification/core.py
superverse/config.py
superverse/dataset/__init__.py
superverse/dataset/core.py
superverse/dataset/formats/__init__.py
superverse/dataset/formats/coco.py
superverse/dataset/formats/pascal_voc.py
superverse/dataset/formats/yolo.py
superverse/dataset/utils.py
superverse/detection/__init__.py
superverse/detection/core.py
superverse/detection/line_zone.py
superverse/detection/lmm.py
superverse/detection/overlap_filter.py
superverse/detection/tools/__init__.py
superverse/detection/tools/csv_sink.py
superverse/detection/tools/inference_slicer.py
superverse/detection/tools/json_sink.py
superverse/detection/tools/polygon_zone.py
superverse/detection/tools/smoother.py
superverse/detection/tools/transformers.py
superverse/detection/utils.py
superverse/draw/__init__.py
superverse/draw/color.py
superverse/draw/utils.py
superverse/geometry/__init__.py
superverse/geometry/core.py
superverse/geometry/utils.py
superverse/keypoint/__init__.py
superverse/keypoint/annotators.py
superverse/keypoint/core.py
superverse/keypoint/skeletons.py
superverse/metrics/__init__.py
superverse/metrics/core.py
superverse/metrics/detection.py
superverse/metrics/f1_score.py
superverse/metrics/mean_average_precision.py
superverse/metrics/mean_average_recall.py
superverse/metrics/precision.py
superverse/metrics/recall.py
superverse/metrics/utils/__init__.py
superverse/metrics/utils/object_size.py
superverse/metrics/utils/utils.py
superverse/py.typed
superverse/tracker/__init__.py
superverse/tracker/byte_tracker/__init__.py
superverse/tracker/byte_tracker/core.py
superverse/tracker/byte_tracker/kalman_filter.py
superverse/tracker/byte_tracker/matching.py
superverse-0.3.0.dist-info/LICENSE.md
superverse-0.3.0.dist-info/METADATA
superverse-0.3.0.dist-info/WHEEL
superverse-0.3.0.dist-info/RECORD
