Metadata-Version: 2.1
Name: superverse
Version: 0.3.0
Summary: A set of easy-to-use utils that will come in handy in any Computer Vision project
Home-page: https://github.com/khulnasoft/superverse
License: MIT
Keywords: machine-learning,deep-learning,vision,ML,DL,AI,Khulnasoft
Author: Md Sulaiman
Author-email: dev.sulaiman@icloud.com
Maintainer: Md Sulaiman
Maintainer-email: dev.sulaiman@icloud.com
Requires-Python: >=3.8,<4.0
Classifier: Development Status :: 4 - Beta
Classifier: Intended Audience :: Developers
Classifier: Intended Audience :: Education
Classifier: Intended Audience :: Science/Research
Classifier: License :: OSI Approved :: MIT License
Classifier: Operating System :: MacOS
Classifier: Operating System :: Microsoft :: Windows
Classifier: Operating System :: POSIX :: Linux
Classifier: Programming Language :: Python :: 3
Classifier: Programming Language :: Python :: 3.8
Classifier: Programming Language :: Python :: 3.9
Classifier: Programming Language :: Python :: 3.10
Classifier: Programming Language :: Python :: 3.11
Classifier: Programming Language :: Python :: 3.12
Classifier: Programming Language :: Python :: 3.13
Classifier: Programming Language :: Python :: 3 :: Only
Classifier: Topic :: Scientific/Engineering
Classifier: Topic :: Scientific/Engineering :: Artificial Intelligence
Classifier: Topic :: Scientific/Engineering :: Image Recognition
Classifier: Topic :: Software Development
Classifier: Typing :: Typed
Provides-Extra: metrics
Requires-Dist: contourpy (>=1.0.7) ; python_version >= "3.8" and python_version < "3.13"
Requires-Dist: contourpy (>=1.3.0) ; python_version >= "3.13"
Requires-Dist: defusedxml (>=0.7.1,<0.8.0)
Requires-Dist: matplotlib (>=3.6.0)
Requires-Dist: numpy (>=1.21.2) ; python_version < "3.13"
Requires-Dist: numpy (>=2.1.0) ; python_version >= "3.13"
Requires-Dist: opencv-python (>=4.5.5.64)
Requires-Dist: pandas (>=2.0.0) ; extra == "metrics"
Requires-Dist: pillow (>=9.4)
Requires-Dist: pyyaml (>=5.3)
Requires-Dist: requests (>=2.26.0)
Requires-Dist: scipy (==1.10.0) ; python_version < "3.9"
Requires-Dist: scipy (>=1.10.0,<2.0.0) ; python_version >= "3.9"
Requires-Dist: scipy (>=1.14.1) ; python_version >= "3.13"
Requires-Dist: tqdm (>=4.62.3)
Project-URL: Documentation, https://superverse.khulnasoft.com/latest/
Project-URL: Repository, https://github.com/khulnasoft/superverse
